{
  "league": "Slovenia Cup",
  "season": "2024/25",
  "matchdays": [
    {
      "matchday": "Round 1",
      "matches": [
        {
          "date": "2024-08-27",
          "time": "17:00",
          "home_team": "Rudar Trbovlje",
          "away_team": "NK Domžale",
          "result": {
            "full_time": "0-5"
          }
        },
        {
          "date": "2024-08-27",
          "time": "17:00",
          "home_team": "NK Dren Vrhnika",
          "away_team": "NK Komenda",
          "result": {
            "full_time": "8-0"
          }
        },
        {
          "date": "2024-08-27",
          "time": "17:30",
          "home_team": "NK Arne Tabor",
          "away_team": "ND Ilirija 1911",
          "result": {
            "full_time": "0-5"
          }
        },
        {
          "date": "2024-08-28",
          "time": "17:00",
          "home_team": "ND Bistrc Irbis",
          "away_team": "Jadran Dekani",
          "result": {
            "full_time": "0-10"
          }
        },
        {
          "date": "2024-08-28",
          "time": "17:00",
          "home_team": "NK Galeb Ankaran",
          "away_team": "FC Koper",
          "result": {
            "full_time": "0-6"
          }
        },
        {
          "date": "2024-08-28",
          "time": "17:00",
          "home_team": "ŠD Košana",
          "away_team": "NK Tabor Sežana",
          "result": {
            "full_time": "0-3"
          }
        },
        {
          "date": "2024-08-28",
          "time": "17:00",
          "home_team": "NK ŠD Kobilje",
          "away_team": "NK Turnišče",
          "result": {
            "full_time": "0-9"
          }
        },
        {
          "date": "2024-08-28",
          "time": "17:00",
          "home_team": "NK Litija",
          "away_team": "NK Kresnice",
          "result": {
            "full_time": "1-0"
          }
        },
        {
          "date": "2024-08-28",
          "time": "17:00",
          "home_team": "NK Bela Krajina",
          "away_team": "Svoboda Ljubljana",
          "result": {
            "full_time": "5-4"
          }
        },
        {
          "date": "2024-08-28",
          "time": "17:00",
          "home_team": "NK Jevnica",
          "away_team": "NK Ivančna Gorica",
          "result": {
            "full_time": "1-0"
          }
        },
        {
          "date": "2024-08-28",
          "time": "17:00",
          "home_team": "IB 1975 Ljubljana",
          "away_team": "NK Krka",
          "result": {
            "full_time": "1-5"
          }
        },
        {
          "date": "2024-08-28",
          "time": "17:00",
          "home_team": "NK Radomlje",
          "away_team": "NK Zagorje",
          "result": {
            "full_time": "14-0"
          }
        },
        {
          "date": "2024-08-28",
          "time": "17:00",
          "home_team": "NK Veržej",
          "away_team": "NŠ Mura",
          "result": {
            "full_time": "0-9"
          }
        },
        {
          "date": "2024-08-28",
          "time": "17:00",
          "home_team": "NK Bogojina",
          "away_team": "NK Tromejnik",
          "result": {
            "full_time": "3-1"
          }
        },
        {
          "date": "2024-08-28",
          "time": "17:00",
          "home_team": "ŠD NK Križevci",
          "away_team": "NK Čarda Martjanci",
          "result": {
            "full_time": "0-6"
          }
        },
        {
          "date": "2024-08-28",
          "time": "17:00",
          "home_team": "NK Gančani",
          "away_team": "NK Ljutomer",
          "result": {
            "full_time": "0-4"
          }
        },
        {
          "date": "2024-08-28",
          "time": "17:00",
          "home_team": "NK Idrija",
          "away_team": "NK Tolmin",
          "result": {
            "full_time": "1-2"
          }
        },
        {
          "date": "2024-08-28",
          "time": "17:00",
          "home_team": "NK Adria",
          "away_team": "NK Vipava",
          "result": {
            "full_time": "1-0"
          }
        },
        {
          "date": "2024-08-28",
          "time": "17:00",
          "home_team": "NK Malibu Panonija",
          "away_team": "NK Polana",
          "result": {
            "full_time": "0-11"
          }
        },
        {
          "date": "2024-08-28",
          "time": "17:00",
          "home_team": "NK Črenšovci",
          "away_team": "NK Odranci",
          "result": {
            "full_time": "0-3"
          }
        },
        {
          "date": "2024-08-28",
          "time": "17:00",
          "home_team": "NK Goričanka Rogašovci",
          "away_team": "NK Dokležovje",
          "result": {
            "full_time": "0-8"
          }
        },
        {
          "date": "2024-08-28",
          "time": "17:00",
          "home_team": "NK Hodoš",
          "away_team": "NK ŠD Ižakovci",
          "result": {
            "full_time": "7-6"
          }
        },
        {
          "date": "2024-08-28",
          "time": "17:00",
          "home_team": "ŠNK Bakovci",
          "away_team": "ŠD Roma",
          "result": {
            "full_time": "3-0"
          }
        },
        {
          "date": "2024-08-28",
          "time": "17:00",
          "home_team": "NK Tišina",
          "away_team": "NK Cankova",
          "result": {
            "full_time": "3-2"
          }
        },
        {
          "date": "2024-08-28",
          "time": "17:00",
          "home_team": "ŠD NK Pušča",
          "away_team": "NK Serdica",
          "result": {
            "full_time": "4-3"
          }
        },
        {
          "date": "2024-08-28",
          "time": "17:00",
          "home_team": "ŠD Cven",
          "away_team": "ND Beltinci",
          "result": {
            "full_time": "0-8"
          }
        },
        {
          "date": "2024-08-28",
          "time": "17:00",
          "home_team": "NK Trebnje",
          "away_team": "Slovan Ljubljana",
          "result": {
            "full_time": "0-3"
          }
        },
        {
          "date": "2024-08-28",
          "time": "18:00",
          "home_team": "NK Korte",
          "away_team": "MNK Izola",
          "result": {
            "full_time": "0-2"
          }
        },
        {
          "date": "2024-08-28",
          "time": "19:00",
          "home_team": "ND Renče",
          "away_team": "ND Bilje",
          "result": {
            "full_time": "0-2"
          }
        },
        {
          "date": "2024-08-28",
          "time": "19:00",
          "home_team": "NK Kamnik",
          "away_team": "Roltek Dob",
          "result": {
            "full_time": "2-7"
          }
        },
        {
          "date": "2024-08-28",
          "time": "20:00",
          "home_team": "ND Gorica",
          "away_team": "ND Primorje",
          "result": {
            "full_time": "4-2"
          }
        },
        {
          "date": "2024-08-29",
          "time": "17:00",
          "home_team": "NK Nedelica",
          "away_team": "NK Virs Bistrica",
          "result": {
            "full_time": "1-12"
          }
        },
        {
          "date": "2024-08-29",
          "time": "17:00",
          "home_team": "NK Graničar Lendava",
          "away_team": "NK Čentiba",
          "result": {
            "full_time": "5-4"
          }
        },
        {
          "date": "2024-09-03",
          "time": "17:00",
          "home_team": "ŠD Gerečja vas",
          "away_team": "NK Aluminij",
          "result": {
            "full_time": "0-3"
          }
        },
        {
          "date": "2024-09-03",
          "time": "17:00",
          "home_team": "NK Makole",
          "away_team": "FC Drava Ptuj",
          "result": {
            "full_time": "4-5"
          }
        },
        {
          "date": "2024-09-03",
          "time": "17:00",
          "home_team": "NK Središče",
          "away_team": "ŠD Videm",
          "result": {
            "full_time": "0-7"
          }
        },
        {
          "date": "2024-09-03",
          "time": "17:00",
          "home_team": "ŠD Apače na Dravskem polju",
          "away_team": "NK Ormož",
          "result": {
            "full_time": "1-0"
          }
        },
        {
          "date": "2024-09-03",
          "time": "17:00",
          "home_team": "NK Tržec",
          "away_team": "NK Zavrč",
          "result": {
            "full_time": "0-9"
          }
        },
        {
          "date": "2024-09-03",
          "time": "17:30",
          "home_team": "NK Storžič-Preddvor",
          "away_team": "Šobec Lesce",
          "result": {
            "full_time": "1-0"
          }
        },
        {
          "date": "2024-09-04",
          "time": "17:00",
          "home_team": "Olimpija Dolga vas",
          "away_team": "NK Nafta",
          "result": {
            "full_time": "0-8"
          }
        },
        {
          "date": "2024-09-04",
          "time": "17:00",
          "home_team": "Tehnotim Pesnica",
          "away_team": "NK ŠD Starše",
          "result": {
            "full_time": "4-3"
          }
        },
        {
          "date": "2024-09-04",
          "time": "17:00",
          "home_team": "Limbuš Pekre",
          "away_team": "NK Dobrovce",
          "result": {
            "full_time": "1-4"
          }
        },
        {
          "date": "2024-09-04",
          "time": "17:00",
          "home_team": "NK Rače",
          "away_team": "Korotan Prevalje",
          "result": {
            "full_time": "3-1"
          }
        },
        {
          "date": "2024-09-04",
          "time": "17:00",
          "home_team": "ŠD Marjeta na Dravskem polju",
          "away_team": "NK Peca",
          "result": {
            "full_time": "6-5"
          }
        },
        {
          "date": "2024-09-04",
          "time": "17:00",
          "home_team": "NK Maribor Tabor",
          "away_team": "NK Jurovski dol",
          "result": {
            "full_time": "3-2"
          }
        },
        {
          "date": "2024-09-04",
          "time": "17:00",
          "home_team": "NK Zgornja Polskava",
          "away_team": "NK Stojnci",
          "result": {
            "full_time": "0-1"
          }
        },
        {
          "date": "2024-09-04",
          "time": "17:00",
          "home_team": "ŠD Bukovci",
          "away_team": "NK Podvinci",
          "result": {
            "full_time": "3-4"
          }
        },
        {
          "date": "2024-09-04",
          "time": "17:00",
          "home_team": "NK Rogoznica",
          "away_team": "NK Hajdina",
          "result": {
            "full_time": "3-5"
          }
        },
        {
          "date": "2024-09-04",
          "time": "17:00",
          "home_team": "NK Gorišnica",
          "away_team": "NK Boč Poljčane",
          "result": {
            "full_time": "4-3"
          }
        },
        {
          "date": "2024-09-04",
          "time": "17:00",
          "home_team": "ŠD Pragersko",
          "away_team": "NK Bistrica",
          "result": {
            "full_time": "0-6"
          }
        },
        {
          "date": "2024-09-04",
          "time": "17:00",
          "home_team": "Škofja Loka",
          "away_team": "NK Žiri",
          "result": {
            "full_time": "1-2"
          }
        },
        {
          "date": "2024-09-04",
          "time": "17:00",
          "home_team": "Polet Sveti Duh",
          "away_team": "NK Tržič",
          "result": {
            "full_time": "7-2"
          }
        },
        {
          "date": "2024-09-04",
          "time": "17:00",
          "home_team": "NK Niko Železniki",
          "away_team": "Medvode",
          "result": {
            "full_time": "5-3"
          }
        },
        {
          "date": "2024-09-04",
          "time": "17:00",
          "home_team": "NK Kranj",
          "away_team": "NK Velesovo Cerklje",
          "result": {
            "full_time": "1-3"
          }
        },
        {
          "date": "2024-09-10",
          "time": "16:00",
          "home_team": "NK Rogaška",
          "away_team": "NK Dravinja",
          "result": {
            "full_time": "0-2"
          }
        },
        {
          "date": "2024-09-10",
          "time": "16:00",
          "home_team": "NK Laško",
          "away_team": "NK Krško",
          "result": {
            "full_time": "2-7"
          }
        },
        {
          "date": "2024-09-10",
          "time": "18:30",
          "home_team": "ND Mozirje",
          "away_team": "NK Žalec",
          "result": {
            "full_time": "4-2"
          }
        },
        {
          "date": "2024-09-11",
          "time": "16:00",
          "home_team": "NK Zreče",
          "away_team": "Rudar Velenje",
          "result": {
            "full_time": "0-3"
          }
        },
        {
          "date": "2024-09-11",
          "time": "17:00",
          "home_team": "NK Triglav",
          "away_team": "SIJ Acroni Jesenice",
          "result": {
            "full_time": "4-0"
          }
        },
        {
          "date": "2024-09-11",
          "time": "19:30",
          "home_team": "NK Brežice 1919",
          "away_team": "NK Šmartno",
          "result": {
            "full_time": "8-1"
          }
        }
      ]
    },
    {
      "matchday": "Round 2",
      "matches": [
        {
          "date": "2024-09-17",
          "time": "16:30",
          "home_team": "NK Dokležovje",
          "away_team": "NK Ljutomer",
          "result": {
            "full_time": "2-1"
          }
        },
        {
          "date": "2024-09-18",
          "time": "16:30",
          "home_team": "NK Virs Bistrica",
          "away_team": "NK Turnišče",
          "result": {
            "full_time": "2-4"
          }
        },
        {
          "date": "2024-09-18",
          "time": "16:30",
          "home_team": "NK Litija",
          "away_team": "ND Ilirija 1911",
          "result": {
            "full_time": "0-1"
          }
        },
        {
          "date": "2024-09-18",
          "time": "16:30",
          "home_team": "NK Bela Krajina",
          "away_team": "Slovan Ljubljana",
          "result": {
            "full_time": "2-1"
          }
        },
        {
          "date": "2024-09-18",
          "time": "16:30",
          "home_team": "NK Jevnica",
          "away_team": "NK Dren Vrhnika",
          "result": {
            "full_time": "0-3"
          }
        },
        {
          "date": "2024-09-18",
          "time": "16:30",
          "home_team": "NK Bravo",
          "away_team": "NK Krka",
          "result": {
            "full_time": "5-0"
          }
        },
        {
          "date": "2024-09-18",
          "time": "16:30",
          "home_team": "NK Bogojina",
          "away_team": "NŠ Mura",
          "result": {
            "full_time": "0-4"
          }
        },
        {
          "date": "2024-09-18",
          "time": "16:30",
          "home_team": "ŠNK Bakovci",
          "away_team": "NK Čarda Martjanci",
          "result": {
            "full_time": "0-7"
          }
        },
        {
          "date": "2024-09-18",
          "time": "16:30",
          "home_team": "ŠD NK Pušča",
          "away_team": "ND Beltinci",
          "result": {
            "full_time": "0-2"
          }
        },
        {
          "date": "2024-09-18",
          "time": "16:30",
          "home_team": "NK Tišina",
          "away_team": "NK Hodoš",
          "result": {
            "full_time": "1-2"
          }
        },
        {
          "date": "2024-09-18",
          "time": "16:30",
          "home_team": "NK Adria",
          "away_team": "NK Tolmin",
          "result": {
            "full_time": "1-3"
          }
        },
        {
          "date": "2024-09-18",
          "time": "16:30",
          "home_team": "NK Storžič-Preddvor",
          "away_team": "NK Žiri",
          "result": {
            "full_time": "5-0"
          }
        },
        {
          "date": "2024-09-18",
          "time": "16:30",
          "home_team": "NK Velesovo Cerklje",
          "away_team": "Polet Sveti Duh",
          "result": {
            "full_time": "2-0"
          }
        },
        {
          "date": "2024-09-18",
          "time": "16:30",
          "home_team": "NK Graničar Lendava",
          "away_team": "NK Nafta",
          "result": {
            "full_time": "0-15"
          }
        },
        {
          "date": "2024-09-18",
          "time": "16:30",
          "home_team": "NK Rače",
          "away_team": "Tehnotim Pesnica",
          "result": {
            "full_time": "2-0"
          }
        },
        {
          "date": "2024-09-18",
          "time": "17:00",
          "home_team": "Jadran Dekani",
          "away_team": "FC Koper",
          "result": {
            "full_time": "1-8"
          }
        },
        {
          "date": "2024-09-18",
          "time": "17:30",
          "home_team": "NK Niko Železniki",
          "away_team": "NK Triglav",
          "result": {
            "full_time": "0-5"
          }
        },
        {
          "date": "2024-09-18",
          "time": "18:30",
          "home_team": "NK Polana",
          "away_team": "NK Odranci",
          "result": {
            "full_time": "1-0"
          }
        },
        {
          "date": "2024-09-18",
          "time": "19:00",
          "home_team": "NK Dobrovce",
          "away_team": "NK Maribor Tabor",
          "result": {
            "full_time": "5-2"
          }
        },
        {
          "date": "2024-09-24",
          "time": "16:30",
          "home_team": "Roltek Dob",
          "away_team": "NK Radomlje",
          "result": {
            "full_time": "0-1"
          }
        },
        {
          "date": "2024-09-24",
          "time": "16:30",
          "home_team": "NK Hajdina",
          "away_team": "NK Aluminij",
          "result": {
            "full_time": "0-4"
          }
        },
        {
          "date": "2024-09-24",
          "time": "16:30",
          "home_team": "ŠD Videm",
          "away_team": "NK Podvinci",
          "result": {
            "full_time": "2-0"
          }
        },
        {
          "date": "2024-09-24",
          "time": "16:30",
          "home_team": "ŠD Apače na Dravskem polju",
          "away_team": "NK Bistrica",
          "result": {
            "full_time": "0-5"
          }
        },
        {
          "date": "2024-09-25",
          "time": "15:30",
          "home_team": "NK Dravinja",
          "away_team": "NK Celje",
          "result": {
            "full_time": "0-3"
          }
        },
        {
          "date": "2024-09-25",
          "time": "16:30",
          "home_team": "ND Gorica",
          "away_team": "ND Bilje",
          "result": {
            "full_time": "0-1"
          }
        },
        {
          "date": "2024-09-25",
          "time": "16:30",
          "home_team": "NK Gorišnica",
          "away_team": "FC Drava Ptuj",
          "result": {
            "full_time": "1-5"
          }
        },
        {
          "date": "2024-09-25",
          "time": "16:30",
          "home_team": "NK Stojnci",
          "away_team": "NK Zavrč",
          "result": {
            "full_time": "1-2"
          }
        },
        {
          "date": "2024-09-25",
          "time": "17:00",
          "home_team": "NK Krško",
          "away_team": "Rudar Velenje",
          "result": {
            "full_time": "1-3"
          }
        },
        {
          "date": "2024-09-25",
          "time": "17:00",
          "home_team": "MNK Izola",
          "away_team": "NK Tabor Sežana",
          "result": {
            "full_time": "0-3"
          }
        },
        {
          "date": "2024-09-25",
          "time": "18:00",
          "home_team": "NK Domžale",
          "away_team": "Olimpija Ljubljana",
          "result": {
            "full_time": "0-3"
          }
        },
        {
          "date": "2024-09-25",
          "time": "18:00",
          "home_team": "ŠD Marjeta na Dravskem polju",
          "away_team": "NK Maribor",
          "result": {
            "full_time": "0-4"
          }
        },
        {
          "date": "2024-09-25",
          "time": "18:30",
          "home_team": "ND Mozirje",
          "away_team": "NK Brežice 1919",
          "result": {
            "full_time": "0-4"
          }
        }
      ]
    },
    {
      "matchday": "Round 3",
      "matches": [
        {
          "date": "2024-10-29",
          "time": "14:00",
          "home_team": "NK Dren Vrhnika",
          "away_team": "NK Bistrica",
          "result": {
            "full_time": "1-3"
          }
        },
        {
          "date": "2024-10-29",
          "time": "14:00",
          "home_team": "ND Beltinci",
          "away_team": "NK Triglav",
          "result": {
            "full_time": "4-0"
          }
        },
        {
          "date": "2024-10-30",
          "time": "14:00",
          "home_team": "ND Bilje",
          "away_team": "FC Koper",
          "result": {
            "full_time": "1-2"
          }
        },
        {
          "date": "2024-10-30",
          "time": "14:00",
          "home_team": "NK Rače",
          "away_team": "NK Brežice 1919",
          "result": {
            "full_time": "3-2"
          }
        },
        {
          "date": "2024-10-30",
          "time": "14:00",
          "home_team": "NK Velesovo Cerklje",
          "away_team": "NK Čarda Martjanci",
          "result": {
            "full_time": "1-3"
          }
        },
        {
          "date": "2024-10-30",
          "time": "14:00",
          "home_team": "NK Hodoš",
          "away_team": "NK Celje",
          "result": {
            "full_time": "0-8"
          }
        },
        {
          "date": "2024-10-30",
          "time": "14:00",
          "home_team": "NK Radomlje",
          "away_team": "Olimpija Ljubljana",
          "result": {
            "full_time": "1-2"
          }
        },
        {
          "date": "2024-10-30",
          "time": "14:00",
          "home_team": "NK Tolmin",
          "away_team": "NK Bravo",
          "result": {
            "full_time": "0-2"
          }
        },
        {
          "date": "2024-10-30",
          "time": "14:00",
          "home_team": "NK Storžič-Preddvor",
          "away_team": "NK Maribor",
          "result": {
            "full_time": "1-2"
          }
        },
        {
          "date": "2024-10-30",
          "time": "16:00",
          "home_team": "Rudar Velenje",
          "away_team": "NK Aluminij",
          "result": {
            "full_time": "1-2"
          }
        },
        {
          "date": "2024-10-30",
          "time": "17:30",
          "home_team": "NŠ Mura",
          "away_team": "NK Zavrč",
          "result": {
            "full_time": "9-0"
          }
        },
        {
          "date": "2024-10-31",
          "time": "12:00",
          "home_team": "ŠD Videm",
          "away_team": "NK Nafta",
          "result": {
            "full_time": "0-3"
          }
        },
        {
          "date": "2024-10-31",
          "time": "12:00",
          "home_team": "NK Turnišče",
          "away_team": "ND Ilirija 1911",
          "result": {
            "full_time": "0-1"
          }
        },
        {
          "date": "2024-10-31",
          "time": "14:00",
          "home_team": "NK Bela Krajina",
          "away_team": "NK Polana",
          "result": {
            "full_time": "1-0"
          }
        },
        {
          "date": "2024-10-31",
          "time": "14:00",
          "home_team": "NK Dokležovje",
          "away_team": "NK Dobrovce",
          "result": {
            "full_time": "2-4"
          }
        },
        {
          "date": "2024-10-31",
          "time": "14:00",
          "home_team": "NK Tabor Sežana",
          "away_team": "FC Drava Ptuj",
          "result": {
            "full_time": "1-0"
          }
        }
      ]
    },
    {
      "matchday": "Round of 16",
      "matches": [
        {
          "date": "2025-02-26",
          "time": "14:30",
          "home_team": "Olimpija Ljubljana",
          "away_team": "ND Ilirija 1911",
          "result": {
            "full_time": "3-0"
          }
        },
        {
          "date": "2025-02-26",
          "time": "16:00",
          "home_team": "NK Celje",
          "away_team": "NK Tabor Sežana",
          "result": {
            "full_time": "3-2"
          }
        },
        {
          "date": "2025-02-26",
          "time": "17:30",
          "home_team": "NŠ Mura",
          "away_team": "FC Koper",
          "result": {
            "full_time": "0-1"
          }
        },
        {
          "date": "2025-03-04",
          "time": "17:30",
          "home_team": "NK Maribor",
          "away_team": "NK Aluminij",
          "result": {
            "full_time": "2-0"
          }
        },
        {
          "date": "2025-03-05",
          "time": "14:30",
          "home_team": "NK Čarda Martjanci",
          "away_team": "NK Nafta",
          "result": {
            "full_time": "1-2"
          }
        },
        {
          "date": "2025-03-05",
          "time": "14:30",
          "home_team": "NK Bravo",
          "away_team": "NK Rače",
          "result": {
            "full_time": "7-0"
          }
        },
        {
          "date": "2025-03-05",
          "time": "18:00",
          "home_team": "NK Dobrovce",
          "away_team": "NK Bistrica",
          "result": {
            "full_time": "0-3"
          }
        },
        {
          "date": "2025-03-06",
          "time": "14:30",
          "home_team": "ND Beltinci",
          "away_team": "NK Bela Krajina",
          "result": {
            "full_time": "10-0"
          }
        }
      ]
    },
    {
      "matchday": "Quarterfinals",
      "matches": [
        {
          "date": "2025-04-01",
          "time": "16:00",
          "home_team": "NK Bistrica",
          "away_team": "FC Koper",
          "result": {
            "full_time": "0-2"
          }
        },
        {
          "date": "2025-04-02",
          "time": "16:00",
          "home_team": "NK Nafta",
          "away_team": "NK Bravo",
          "result": {
            "full_time": "4-5"
          }
        },
        {
          "date": "2025-04-02",
          "time": "19:00",
          "home_team": "NK Maribor",
          "away_team": "NK Celje",
          "result": {
            "full_time": "0-1"
          }
        },
        {
          "date": "2025-04-03",
          "time": "16:00",
          "home_team": "Olimpija Ljubljana",
          "away_team": "ND Beltinci",
          "result": {
            "full_time": "5-2"
          }
        }
      ]
    },
    {
      "matchday": "Semifinals",
      "matches": [
        {
          "date": "2025-04-23",
          "time": "18:00",
          "home_team": "FC Koper",
          "away_team": "NK Bravo",
          "result": {
            "full_time": "3-0"
          }
        },
        {
          "date": "2025-04-24",
          "time": "18:00",
          "home_team": "NK Celje",
          "away_team": "Olimpija Ljubljana",
          "result": {
            "full_time": "2-1"
          }
        }
      ]
    },
    {
      "matchday": "Final",
      "matches": [
        {
          "date": "2025-05-14",
          "time": "20:00",
          "home_team": "FC Koper",
          "away_team": "NK Celje"
        }
      ]
    }
  ]
}